dem_stitcher/__init__.py
dem_stitcher/credentials.py
dem_stitcher/datasets.py
dem_stitcher/dateline.py
dem_stitcher/dem_readers.py
dem_stitcher/exceptions.py
dem_stitcher/geoid.py
dem_stitcher/geojson_io.py
dem_stitcher/merge.py
dem_stitcher/rio_tools.py
dem_stitcher/rio_window.py
dem_stitcher/stitcher.py
dem_stitcher/data/3dep.geojson.zip
dem_stitcher/data/egm96_15.gtx
dem_stitcher/data/geoid_18.tif
dem_stitcher/data/glo_30.geojson.zip
dem_stitcher/data/glo_90.geojson.zip
dem_stitcher/data/glo_90_missing.geojson.zip
dem_stitcher/data/nasadem.geojson.zip
dem_stitcher/data/srtm_v3.geojson.zip
dem_stitcher-2.5.11.dist-info/LICENSE.txt
dem_stitcher-2.5.11.dist-info/METADATA
dem_stitcher-2.5.11.dist-info/WHEEL
dem_stitcher-2.5.11.dist-info/top_level.txt
dem_stitcher-2.5.11.dist-info/zip-safe
dem_stitcher-2.5.11.dist-info/RECORD
