Metadata-Version: 2.1
Name: dem_stitcher
Version: 2.5.11
Summary: Download and merge DEM tiles
Author-email: "Charlie Marshak, David Bekaert, Michael Denbina, Marc Simard, Joseph H. Kennedy, Simran Sangha, Grace Bato" <access_cloud_based_insar@jpl.nasa.gov>
License: Apache-2.0
Project-URL: Homepage, https://github.com/ACCESS-Cloud-Based-InSAR/dem-stitcher
Project-URL: Bug Tracker, https://github.com/ACCESS-Cloud-Based-InSAR/dem-stitcher/issues
Classifier: Intended Audience :: Science/Research
Classifier: Natural Language :: English
Classifier: Operating System :: OS Independent
Classifier: Natural Language :: English
Classifier: Programming Language :: Python :: 3
Classifier: Programming Language :: Python :: 3.9
Classifier: Programming Language :: Python :: 3.10
Classifier: Programming Language :: Python :: 3.11
Classifier: Programming Language :: Python :: 3.12
Classifier: Programming Language :: Python :: 3.13
Requires-Python: >=3.9
License-File: LICENSE.txt
Requires-Dist: affine
Requires-Dist: boto3
Requires-Dist: geopandas
Requires-Dist: importlib_metadata
Requires-Dist: numpy
Requires-Dist: pyproj
Requires-Dist: rasterio
Requires-Dist: requests
Requires-Dist: shapely
Requires-Dist: tqdm
Provides-Extra: develop
Requires-Dist: pytest; extra == "develop"
Requires-Dist: pytest-cov; extra == "develop"
Requires-Dist: flake8; extra == "develop"
Requires-Dist: flake8-import-order; extra == "develop"
Requires-Dist: flake8-blind-except; extra == "develop"
Requires-Dist: flake8-builtins; extra == "develop"
